xdrlib.py
py_xdrlib-4.0.2.dist-info/LICENSE
py_xdrlib-4.0.2.dist-info/WHEEL
py_xdrlib-4.0.2.dist-info/METADATA
py_xdrlib-4.0.2.dist-info/RECORD
