Metadata-Version: 2.1
Name: py-xdrlib
Version: 4.0.2
Summary: Encode or decode XDR (IETF RFC-4506/1832/1014)
Author-email: David Arnold <davida@pobox.com>
Requires-Python: >=3.8
Classifier: Programming Language :: Python :: 3
Classifier: License :: OSI Approved :: Python Software Foundation License
Classifier: Operating System :: OS Independent
Project-URL: Bug Tracker, https://github.com/da4089/py-xdrlib/issues
Project-URL: Homepage, https://github.com/da4089/py-xdrlib
